<?xml version="1.0" encoding="UTF-8" standalone="yes"?>
<slicerCacheDefinition xmlns="http://schemas.microsoft.com/office/spreadsheetml/2009/9/main" xmlns:mc="http://schemas.openxmlformats.org/markup-compatibility/2006" mc:Ignorable="x xr10" xmlns:x="http://schemas.openxmlformats.org/spreadsheetml/2006/main" xmlns:xr10="http://schemas.microsoft.com/office/spreadsheetml/2016/revision10" name="SegmentaciónDeDatos_Modelos" xr10:uid="{8BBC7E9D-B444-4EBA-B8AB-CD22FC07AEF8}" sourceName="Modelos"><pivotTables><pivotTable tabId="5" name="TablaDinámica3"/></pivotTables><data><tabular pivotCacheId="1110882159"><items count="29"><i x="0"/><i x="1"/><i x="2"/><i x="24"/><i x="25"/><i x="26"/><i x="27"/><i x="28"/><i x="3"/><i x="4"/><i x="5"/><i x="6"/><i x="7"/><i x="8"/><i x="9"/><i x="10"/><i x="11"/><i x="12"/><i x="13"/><i x="14"/><i x="15"/><i x="16"/><i x="17"/><i x="18"/><i x="19"/><i x="20"/><i x="21" s="1"/><i x="22"/><i x="23"/></items></tabular></data></slicerCacheDefinition>